TwinCAT3_plc_files_to_src.py
TwinCAT3_plc_files_to_src-0.0.13.dist-info/LICENSE
TwinCAT3_plc_files_to_src-0.0.13.dist-info/METADATA
TwinCAT3_plc_files_to_src-0.0.13.dist-info/WHEEL
TwinCAT3_plc_files_to_src-0.0.13.dist-info/top_level.txt
TwinCAT3_plc_files_to_src-0.0.13.dist-info/RECORD
