Metadata-Version: 2.1
Name: TwinCAT3-plc-files-to-src
Version: 0.0.13
Summary: desc
Home-page: https://github.com/TobiasFreyermuth/TwinCAT3_plc_files_to_src
Author: Tobias Freyermuth
Author-email: Tobias.Freyermuth@posteo.net
License: MIT
Classifier: Development Status :: 4 - Beta
Classifier: Intended Audience :: Developers
Classifier: License :: OSI Approved :: MIT License
Classifier: Programming Language :: Python
Classifier: Programming Language :: Python :: 3 :: Only
Classifier: Programming Language :: Python :: 3.7
Requires-Python: >=3.7
License-File: LICENSE
Requires-Dist: lxml (>=4.0.0)
Provides-Extra: dev
Requires-Dist: pytest (>=7.0) ; extra == 'dev'
